pyaki/__init__.py
pyaki/bin/__init__.py
pyaki/bin/process_aki_stages.py
pyaki/kdigo.py
pyaki/preprocessors.py
pyaki/probes.py
pyaki/py.typed
pyaki/utils.py
pyaki-1.0.11.dist-info/AUTHORS
pyaki-1.0.11.dist-info/LICENSE
pyaki-1.0.11.dist-info/METADATA
pyaki-1.0.11.dist-info/WHEEL
pyaki-1.0.11.dist-info/entry_points.txt
pyaki-1.0.11.dist-info/RECORD
