Metadata-Version: 2.3
Name: pyaki
Version: 1.0.11
Summary: pyAKI allows calculation of Acute Kidney Injury from urine output and creatinine based on KDIGO criteria.
License: MIT
Keywords: AKI,Data,ICU,Healthcare,Analysis
Author: ADIH MS
Requires-Python: >=3.12,<4.0
Classifier: Intended Audience :: Developers
Classifier: Intended Audience :: Science/Research
Classifier: License :: OSI Approved :: MIT License
Classifier: Operating System :: OS Independent
Classifier: Programming Language :: Python :: 3
Classifier: Programming Language :: Python :: 3.12
Classifier: Programming Language :: Python :: 3.13
Requires-Dist: pandas (>=2.2.3,<3.0.0)
Requires-Dist: pandas-stubs (>=2.2.3.241126,<3.0.0.0)
Requires-Dist: scipy (>=1.15.0,<2.0.0)
Requires-Dist: typer[all] (>=0.9,<0.16)
Project-URL: Bugtracker, https://github.com/AI2MS/pyAKI/issues
Project-URL: Changelog, https://github.com/AI2MS/pyAKI/releases
Project-URL: Documentation, https://github.com/AI2MS/pyAKI
Project-URL: Homepage, https://github.com/AI2MS/pyAKI
Project-URL: Repository, https://github.com/AI2MS/pyAKI
